{
    "Ar36": {
        "error": 0.0020435609889500393, 
        "fit": "linear", 
        "value": 0.025516357712095573
    }, 
    "Ar37": {
        "error": 0.14998250174936933, 
        "fit": "linear", 
        "value": 0.077356281116213774
    }, 
    "Ar38": {
        "error": 0.27077391774492643, 
        "fit": "linear", 
        "value": 0.58435231237078189
    }, 
    "Ar39": {
        "error": 0.087605469880719863, 
        "fit": "linear", 
        "value": 54.131600405559574
    }, 
    "Ar40": {
        "error": 0.67270174221255885, 
        "fit": "linear", 
        "value": 2364.59414041736
    }, 
    "Ar41": {
        "error": 0.11373467775059155, 
        "fit": "average_SEM", 
        "value": 0.25393051913189185
    }
}