{
    "Ar36": {
        "error": 0.0015566953191263877, 
        "fit": "linear", 
        "value": 0.013686191446741372
    }, 
    "Ar37": {
        "error": 0.13397014401180252, 
        "fit": "linear", 
        "value": 0.028434511910466392
    }, 
    "Ar38": {
        "error": 0.25300545017375353, 
        "fit": "linear", 
        "value": 0.23956524895840725
    }, 
    "Ar39": {
        "error": 0.072698123832864697, 
        "fit": "linear", 
        "value": 27.051142477282369
    }, 
    "Ar40": {
        "error": 0.43160794706480804, 
        "fit": "linear", 
        "value": 1187.7240790908731
    }, 
    "Ar41": {
        "error": 0.12485228826482844, 
        "fit": "average_SEM", 
        "value": -0.039179050567973821
    }
}