{
    "Ar36": {
        "error": 0.0017651066417547008, 
        "fit": "linear", 
        "value": 0.01598060398704643
    }, 
    "Ar37": {
        "error": 0.1288065805641303, 
        "fit": "linear", 
        "value": -0.00036212094313497773
    }, 
    "Ar38": {
        "error": 0.25602504573749729, 
        "fit": "linear", 
        "value": 0.31157787021675576
    }, 
    "Ar39": {
        "error": 0.077045443620543885, 
        "fit": "linear", 
        "value": 34.366025039263484
    }, 
    "Ar40": {
        "error": 0.53536621019905994, 
        "fit": "linear", 
        "value": 1503.9053749669147
    }, 
    "Ar41": {
        "error": 0.12411905937162088, 
        "fit": "average_SEM", 
        "value": -0.023579551447053544
    }
}