{
    "Ar36": {
        "error": 0.0019546171052729116, 
        "fit": "linear", 
        "value": 0.0236367141410165
    }, 
    "Ar37": {
        "error": 0.14508203890305291, 
        "fit": "linear", 
        "value": -0.00049614770678536868
    }, 
    "Ar38": {
        "error": 0.15828507595619223, 
        "fit": "linear", 
        "value": 0.29137935974338991
    }, 
    "Ar39": {
        "error": 0.074414293317790023, 
        "fit": "linear", 
        "value": 31.60532282629881
    }, 
    "Ar40": {
        "error": 0.51496629553091378, 
        "fit": "linear", 
        "value": 1384.5300847055141
    }, 
    "Ar41": {
        "error": 0.13817953040565284, 
        "fit": "average_SEM", 
        "value": -0.040387539627974749
    }
}