{
    "Ar36": {
        "error": 0.001519668781911557, 
        "fit": "parabolic", 
        "value": 0.011574664286906407
    }, 
    "Ar37": {
        "error": 0.13619177580311206, 
        "fit": "linear", 
        "value": -0.096620041118328864
    }, 
    "Ar38": {
        "error": 0.21592097706200178, 
        "fit": "linear", 
        "value": -0.14615202584474574
    }, 
    "Ar39": {
        "error": 0.05956016268242454, 
        "fit": "parabolic", 
        "value": 0.015840579291109286
    }, 
    "Ar40": {
        "error": 0.12529305813085473, 
        "fit": "parabolic", 
        "value": 3.5433173140809151
    }, 
    "Ar41": {
        "error": 0.12146540186971952, 
        "fit": "average_SEM", 
        "value": -0.061845709801418708
    }
}